pyttest.py
python_ttest-1.0.1.dist-info/LICENSE
python_ttest-1.0.1.dist-info/METADATA
python_ttest-1.0.1.dist-info/WHEEL
python_ttest-1.0.1.dist-info/top_level.txt
python_ttest-1.0.1.dist-info/RECORD
