Metadata-Version: 2.1
Name: python-ttest
Version: 1.0.1
Summary: A Python package specifically for Student's t-test.
Author: Crowthebird
License: BSD 3-Clause License
Project-URL: Source, https://github.com/thatbirdguythatuknownot/python-t-test/
Keywords: ttest,student,t-test
Classifier: License :: OSI Approved :: BSD License
Classifier: Programming Language :: Python
Classifier: Programming Language :: Python :: 3
Classifier: Programming Language :: Python :: 3 :: Only
Requires-Python: >=3.9
License-File: LICENSE
